{"templateName":"icon-button-probe-1","componentsTree":{"key":"node1","type":"PAGE_COMPONENT_TYPE","props":{"componentName":"usr.in-page-components.button.IconButton","componentInstance":"iconButton","errors":{"COMPILER_ERROR_INSTANCE_HAS_PROPERTIES_ERRORS":"The iconButton instance has errors in properties."},"isSelected":true},"index":0,"children":[{"key":"node2","type":"COMPONENT_PROPERTY_ONE_OF_TYPE","props":{"propertyName":"color","propertyComment":"\n The color of the component. It supports those theme colors that make sense for this component.\n","propertyValueVariants":[{"value":"default"},{"value":"inherit"},{"value":"primary"},{"value":"secondary"}],"propertyValue":""},"index":0},{"key":"node3","type":"COMPONENT_PROPERTY_BOOL_TYPE","props":{"propertyName":"disabled","propertyComment":"\n If true, the button will be disabled.\n","propertyValue":false},"index":1},{"key":"node4","type":"COMPONENT_PROPERTY_BOOL_TYPE","props":{"propertyName":"doNotUseInFlows","propertyComment":"\n If true then the component's instance will not be allowed to use in flows,\n and you will not see the instance name in the pages instances list\n"},"index":2},{"key":"node5","type":"COMPONENT_PROPERTY_ONE_OF_TYPE","props":{"propertyName":"edge","propertyComment":"\n If given, uses a negative margin to counteract the padding on one side\n (this is often helpful for aligning the left or right side of the icon with content above or below,\n without ruining the border size and shape).\n","propertyValueVariants":[{"value":"start"},{"value":"end"},{"value":"false"}],"propertyValue":""},"index":3},{"key":"node6","type":"COMPONENT_PROPERTY_ELEMENT_TYPE","props":{"propertyName":"icon","propertyComment":"\n Icon\n","componentName":"__PlaceHolder"},"index":4},{"key":"node14","type":"COMPONENT_PROPERTY_BOOL_TYPE","props":{"propertyName":"loading","propertyComment":"\n If true the circular progress is shown and button is disabled.\n","propertyValue":false},"index":6},{"key":"node15","type":"COMPONENT_PROPERTY_FUNCTION_TYPE","props":{"propertyName":"onClick","propertyComment":"\n Triggered when the user click on the button\n\n","externalProperties":"usr.in-page-components.button.IconButton.IconButtonOnClickTypes"},"index":7},{"key":"node16","type":"COMPONENT_PROPERTY_ONE_OF_TYPE","props":{"propertyName":"size","propertyComment":"\n The size of the button. `small` is equivalent to the dense button styling.\n","propertyValueVariants":[{"value":"small"},{"value":"medium"}],"propertyValue":"small"},"index":8}]}}