{"pageName":"main","pagePath":"main","componentsTree":{"key":"node137","type":"PAGE_COMPONENT_TYPE","props":{"componentName":"usr.page-frames.pwa.default-frame.PageFrame","componentInstance":"pageFrame","isSelected":true},"index":0,"children":[{"key":"node138","type":"COMPONENT_PROPERTY_SHAPE_TYPE","props":{"propertyName":"drawer","propertyComment":"Drawer props"},"index":0,"children":[{"key":"node140","type":"COMPONENT_PROPERTY_ELEMENT_TYPE","props":{"propertyName":"drawerContent","componentName":"__PlaceHolder","propertyComment":"The component inside the drawer."},"index":0},{"key":"node141","type":"COMPONENT_PROPERTY_STRING_TYPE","props":{"propertyName":"drawerWidth","propertyComment":"The width of the drawer. Should be a string value with the width units.","propertyValue":"250px"},"index":1}]},{"key":"node142","type":"COMPONENT_PROPERTY_SHAPE_TYPE","props":{"propertyName":"toolbar"},"index":1,"children":[{"key":"node144","type":"COMPONENT_PROPERTY_ONE_OF_TYPE","props":{"propertyName":"elevation","propertyValueVariants":[{"value":"0"},{"value":"1"},{"value":"2"},{"value":"3"},{"value":"4"},{"value":"5"},{"value":"6"},{"value":"7"},{"value":"8"},{"value":"9"},{"value":"10"},{"value":"11"},{"value":"12"},{"value":"13"},{"value":"14"},{"value":"15"},{"value":"16"},{"value":"17"},{"value":"18"},{"value":"19"},{"value":"20"},{"value":"21"},{"value":"22"},{"value":"23"},{"value":"24"}],"propertyComment":"Shadow depth. It accepts values between 0 and 24 inclusive.","propertyValue":"2"},"index":0},{"key":"node145","type":"COMPONENT_PROPERTY_STRING_TYPE","props":{"propertyName":"toolbarTitle","propertyComment":"A title of the toolbar. String value.","propertyValue":"Home"},"index":1},{"key":"node146","type":"COMPONENT_PROPERTY_ONE_OF_TYPE","props":{"propertyName":"toolbarTitleVariant","propertyValueVariants":[{"value":"h1"},{"value":"h2"},{"value":"h3"},{"value":"h4"},{"value":"h5"},{"value":"h6"},{"value":"subtitle1"},{"value":"subtitle2"},{"value":"body1"},{"value":"body2"},{"value":"button"},{"value":"caption"},{"value":"overline"},{"value":"inherit"}],"propertyComment":"Title style variant","propertyValue":"h6"},"index":2}]}]}}